<annotation><filename>img_20141211_095650.jpg</filename><folder>users/snsumba//necrosis</folder><source><submittedBy>solomon nsumba</submittedBy></source><imagesize><nrows>2328</nrows><ncols>2320</ncols></imagesize><object><name>Area</name><deleted>0</deleted><verified>0</verified><occluded>no</occluded><attributes></attributes><parts><hasparts></hasparts><ispartof></ispartof></parts><date>20-Jul-2015 17:38:55</date><id>0</id><polygon><username>anonymous</username><pt><x>32</x><y>951</y></pt><pt><x>75</x><y>813</y></pt><pt><x>103</x><y>718</y></pt><pt><x>162</x><y>619</y></pt><pt><x>209</x><y>493</y></pt><pt><x>280</x><y>414</y></pt><pt><x>308</x><y>351</y></pt><pt><x>414</x><y>217</y></pt><pt><x>481</x><y>170</y></pt><pt><x>529</x><y>130</y></pt><pt><x>580</x><y>107</y></pt><pt><x>655</x><y>59</y></pt><pt><x>718</x><y>36</y></pt><pt><x>773</x><y>8</y></pt><pt><x>1598</x><y>8</y></pt><pt><x>1681</x><y>63</y></pt><pt><x>1819</x><y>178</y></pt><pt><x>1858</x><y>241</y></pt><pt><x>1870</x><y>300</y></pt><pt><x>1855</x><y>371</y></pt><pt><x>1851</x><y>391</y></pt><pt><x>1878</x><y>351</y></pt><pt><x>1933</x><y>466</y></pt><pt><x>2001</x><y>612</y></pt><pt><x>2119</x><y>698</y></pt><pt><x>2206</x><y>829</y></pt><pt><x>2261</x><y>951</y></pt><pt><x>2265</x><y>1006</y></pt><pt><x>2206</x><y>1022</y></pt><pt><x>2194</x><y>1105</y></pt><pt><x>2221</x><y>1148</y></pt><pt><x>2249</x><y>1211</y></pt><pt><x>2253</x><y>1267</y></pt><pt><x>2289</x><y>1294</y></pt><pt><x>2316</x><y>1338</y></pt><pt><x>2312</x><y>1405</y></pt><pt><x>2261</x><y>1417</y></pt><pt><x>2221</x><y>1464</y></pt><pt><x>2225</x><y>1543</y></pt><pt><x>2269</x><y>1618</y></pt><pt><x>2269</x><y>1693</y></pt><pt><x>2221</x><y>1874</y></pt><pt><x>2135</x><y>2024</y></pt><pt><x>2064</x><y>2091</y></pt><pt><x>1878</x><y>2233</y></pt><pt><x>1657</x><y>2312</y></pt><pt><x>1377</x><y>2324</y></pt><pt><x>951</x><y>2312</y></pt><pt><x>698</x><y>2202</y></pt><pt><x>584</x><y>2139</y></pt><pt><x>525</x><y>2072</y></pt><pt><x>462</x><y>2001</y></pt><pt><x>371</x><y>1847</y></pt><pt><x>276</x><y>1728</y></pt><pt><x>158</x><y>1645</y></pt><pt><x>67</x><y>1590</y></pt><pt><x>36</x><y>1563</y></pt><pt><x>47</x><y>1543</y></pt><pt><x>59</x><y>1523</y></pt><pt><x>55</x><y>1480</y></pt><pt><x>20</x><y>1480</y></pt><pt><x>0</x><y>1413</y></pt><pt><x>8</x><y>1393</y></pt><pt><x>16</x><y>1357</y></pt><pt><x>12</x><y>1290</y></pt><pt><x>0</x><y>1101</y></pt><pt><x>20</x><y>1057</y></pt><pt><x>28</x><y>1002</y></pt><pt><x>32</x><y>986</y></pt></polygon></object><object><name>necrosis</name><deleted>0</deleted><verified>0</verified><occluded>no</occluded><attributes></attributes><parts><hasparts></hasparts><ispartof></ispartof></parts><date>20-Jul-2015 17:39:11</date><id>1</id><polygon><username>anonymous</username><pt><x>1101</x><y>1271</y></pt><pt><x>1144</x><y>1203</y></pt><pt><x>1180</x><y>1200</y></pt><pt><x>1255</x><y>1207</y></pt><pt><x>1290</x><y>1184</y></pt><pt><x>1290</x><y>1227</y></pt><pt><x>1302</x><y>1251</y></pt><pt><x>1302</x><y>1294</y></pt><pt><x>1259</x><y>1330</y></pt><pt><x>1196</x><y>1314</y></pt><pt><x>1140</x><y>1306</y></pt><pt><x>1121</x><y>1302</y></pt></polygon></object><object><name>necrosis</name><deleted>0</deleted><verified>0</verified><occluded>no</occluded><attributes></attributes><parts><hasparts></hasparts><ispartof></ispartof></parts><date>20-Jul-2015 17:40:35</date><id>2</id><polygon><username>anonymous</username><pt><x>679</x><y>185</y></pt><pt><x>687</x><y>107</y></pt><pt><x>706</x><y>55</y></pt><pt><x>911</x><y>12</y></pt><pt><x>1054</x><y>8</y></pt><pt><x>1263</x><y>16</y></pt><pt><x>1456</x><y>12</y></pt><pt><x>1582</x><y>4</y></pt><pt><x>1712</x><y>91</y></pt><pt><x>1831</x><y>185</y></pt><pt><x>1878</x><y>316</y></pt><pt><x>1874</x><y>379</y></pt><pt><x>1906</x><y>406</y></pt><pt><x>2032</x><y>651</y></pt><pt><x>2162</x><y>746</y></pt><pt><x>2233</x><y>904</y></pt><pt><x>2273</x><y>994</y></pt><pt><x>2237</x><y>1010</y></pt><pt><x>2206</x><y>1061</y></pt><pt><x>2237</x><y>1160</y></pt><pt><x>2253</x><y>1235</y></pt><pt><x>2292</x><y>1310</y></pt><pt><x>2308</x><y>1385</y></pt><pt><x>2221</x><y>1436</y></pt><pt><x>2237</x><y>1531</y></pt><pt><x>2245</x><y>1582</y></pt><pt><x>2214</x><y>1598</y></pt><pt><x>2170</x><y>1566</y></pt><pt><x>2162</x><y>1448</y></pt><pt><x>2190</x><y>1247</y></pt><pt><x>2139</x><y>1054</y></pt><pt><x>2091</x><y>923</y></pt><pt><x>2036</x><y>844</y></pt><pt><x>1997</x><y>805</y></pt><pt><x>1953</x><y>793</y></pt><pt><x>1882</x><y>884</y></pt><pt><x>1772</x><y>793</y></pt><pt><x>1780</x><y>706</y></pt><pt><x>1732</x><y>604</y></pt><pt><x>1709</x><y>513</y></pt><pt><x>1705</x><y>462</y></pt><pt><x>1732</x><y>426</y></pt><pt><x>1803</x><y>458</y></pt><pt><x>1811</x><y>537</y></pt><pt><x>1866</x><y>651</y></pt><pt><x>1933</x><y>718</y></pt><pt><x>2056</x><y>797</y></pt><pt><x>2135</x><y>947</y></pt><pt><x>2178</x><y>1010</y></pt><pt><x>2186</x><y>955</y></pt><pt><x>2099</x><y>762</y></pt><pt><x>1906</x><y>584</y></pt><pt><x>1827</x><y>458</y></pt><pt><x>1752</x><y>367</y></pt><pt><x>1657</x><y>284</y></pt><pt><x>1586</x><y>221</y></pt><pt><x>1610</x><y>134</y></pt><pt><x>1539</x><y>142</y></pt><pt><x>1326</x><y>107</y></pt><pt><x>1117</x><y>99</y></pt><pt><x>1164</x><y>114</y></pt><pt><x>1125</x><y>182</y></pt><pt><x>1014</x><y>217</y></pt><pt><x>817</x><y>229</y></pt><pt><x>746</x><y>193</y></pt><pt><x>714</x><y>178</y></pt></polygon></object></annotation>